{"cameraMode":{"drawMode":0,"name":"Shaded","section":"Shading Mode"},"sceneLighting":true,"audioPlay":false,"sceneViewState":{"m_AlwaysRefresh":false,"showFog":true,"showSkybox":true,"showFlares":true,"showImageEffects":true,"showParticleSystems":true,"showVisualEffectGraphs":true,"m_FxEnabled":true},"in2DMode":false,"pivot":{"x":17.838396072387697,"y":-33.38549041748047,"z":0.5765382647514343},"rotation":{"x":0.31801512837409975,"y":-0.05997453257441521,"z":0.020166652277112008,"w":0.9459736347198486},"size":10.0,"orthographic":false}